{
  "allFiles": [
    {
      "file": "/storage/emulated/0/AndroidIDEProjects/vcore/vcore/build.gradle",
      "selection": {
        "end": {
          "column": 5,
          "index": 703,
          "line": 36
        },
        "start": {
          "column": 5,
          "index": 703,
          "line": 36
        }
      }
    },
    {
      "file": "/storage/emulated/0/AndroidIDEProjects/vcore/vcore/src/main/cpp/vphone_core.cpp",
      "selection": {
        "end": {
          "column": 0,
          "index": 989,
          "line": 32
        },
        "start": {
          "column": 0,
          "index": 989,
          "line": 32
        }
      }
    },
    {
      "file": "/storage/emulated/0/AndroidIDEProjects/vcore/vcore/src/main/java/com/aar/test/virtual/VHookCore.java",
      "selection": {
        "end": {
          "column": 0,
          "index": 3523,
          "line": 97
        },
        "start": {
          "column": 0,
          "index": 3523,
          "line": 97
        }
      }
    }
  ],
  "selectedFile": "/storage/emulated/0/AndroidIDEProjects/vcore/vcore/build.gradle"
}